LICENSE.txt
MANIFEST.in
README.rst
ldif_lexer.py
setup.py
pygments_ldif.egg-info/PKG-INFO
pygments_ldif.egg-info/SOURCES.txt
pygments_ldif.egg-info/dependency_links.txt
pygments_ldif.egg-info/entry_points.txt
pygments_ldif.egg-info/requires.txt
pygments_ldif.egg-info/top_level.txt