Metadata-Version: 1.0
Name: pygments-ldif
Version: 1.0.1
Summary: LDAP Data Interchange Format (LDIF) lexer for Pygments
Home-page: http://projects.skurfer.com/posts/2011/ldif_pygments/
Author: Rob McBroom
Author-email: pygments-ldif@skurfer.com
License: MIT License
Platform: UNKNOWN
